[
  {
    "home": "Macclesfield",
    "away": "Brentford",
    "times": {
      "Flashscore": "19:30",
      "Betika": "19:30",
      "Odibets": "22:30"
    },
    "league": "Unknown",
    "timestamp": "2026-02-16 08:45:16"
  },
  {
    "home": "Beitar Jerusalem",
    "away": "Maccabi Tel Aviv",
    "times": {
      "Flashscore": "18:30",
      "Betika": "18:30",
      "Odibets": "21:30"
    },
    "league": "Unknown",
    "timestamp": "2026-02-16 08:45:16"
  },
  {
    "home": "Coventry",
    "away": "Middlesbrough",
    "times": {
      "Flashscore": "20:00",
      "Betika": "20:00",
      "Odibets": "23:00"
    },
    "league": "Unknown",
    "timestamp": "2026-02-16 08:45:16"
  },
  {
    "home": "Macclesfield Fc",
    "away": "Brentford",
    "times": {
      "Betika": "19:30",
      "Odibets": "22:30"
    },
    "league": "England \u2022 FA Cup",
    "timestamp": "2026-02-16 10:33:48"
  },
  {
    "home": "Coventry",
    "away": "Middlesbrough",
    "times": {
      "Flashscore": "23:00",
      "Betika": "20:00",
      "Odibets": "23:00"
    },
    "league": "England: Championship",
    "timestamp": "2026-02-16 10:33:48"
  },
  {
    "home": "Girona",
    "away": "Barcelona",
    "times": {
      "Flashscore": "23:00",
      "Betika": "20:00"
    },
    "league": "Spain: LaLiga",
    "timestamp": "2026-02-16 10:33:48"
  },
  {
    "home": "Beitar Jerusalem",
    "away": "Maccabi Tel Aviv",
    "times": {
      "Betika": "18:30",
      "Odibets": "21:30"
    },
    "league": "Israel \u2022 Premier League",
    "timestamp": "2026-02-16 10:33:48"
  },
  {
    "home": "Albion",
    "away": "CA Cerro",
    "times": {
      "Flashscore": "01:00",
      "Betika": "22:00"
    },
    "league": "Uruguay: Liga AUF Uruguaya - Apertura",
    "timestamp": "2026-02-16 10:33:48"
  },
  {
    "home": "Quindio",
    "away": "Barranquilla",
    "times": {
      "Flashscore": "03:30",
      "Betika": "00:30"
    },
    "league": "Colombia: Primera B - Apertura",
    "timestamp": "2026-02-16 10:33:48"
  },
  {
    "home": "Fluminense",
    "away": "Bangu",
    "times": {
      "Flashscore": "00:00",
      "Betika": "21:00"
    },
    "league": "Brazil: Carioca - Taca Guanabara - Play Offs",
    "timestamp": "2026-02-16 10:33:48"
  },
  {
    "home": "Rio Ave",
    "away": "Moreirense",
    "times": {
      "Flashscore": "23:15",
      "Odibets": "23:15",
      "MozzartBet": "20:15"
    },
    "league": "Portugal: Liga Portugal",
    "date": "16/02",
    "timestamp": "2026-02-16 11:50:32"
  },
  {
    "home": "Quindio",
    "away": "Barranquilla",
    "times": {
      "Flashscore": "03:30",
      "MozzartBet": "00:30"
    },
    "league": "Colombia: Primera B - Apertura",
    "date": "17/02",
    "timestamp": "2026-02-16 11:50:32"
  },
  {
    "home": "Nova Iguacu",
    "away": "Marica",
    "times": {
      "Flashscore": "23:00",
      "MozzartBet": "20:00"
    },
    "league": "Brazil: Carioca - Relegation Group",
    "date": "16/02",
    "timestamp": "2026-02-16 11:50:32"
  },
  {
    "home": "Santos W",
    "away": "Gremio W",
    "times": {
      "Flashscore": "01:00",
      "MozzartBet": "22:00"
    },
    "league": "Brazil: Brasileiro Women",
    "date": "17/02",
    "timestamp": "2026-02-16 11:50:32"
  },
  {
    "home": "Fluminense",
    "away": "Bangu",
    "times": {
      "Flashscore": "00:00",
      "MozzartBet": "21:00"
    },
    "league": "Brazil: Carioca - Taca Guanabara - Play Offs",
    "date": "17/02",
    "timestamp": "2026-02-16 11:50:32"
  },
  {
    "home": "Macclesfield FC",
    "away": "Brentford FC",
    "times": {
      "Odibets": "22:30",
      "MozzartBet": "19:30"
    },
    "league": "Football",
    "date": "16/02",
    "timestamp": "2026-02-16 11:50:32"
  },
  {
    "home": "Girona",
    "away": "Barcelona",
    "times": {
      "Flashscore": "23:00",
      "MozzartBet": "20:00"
    },
    "league": "Spain: LaLiga",
    "date": "16/02",
    "timestamp": "2026-02-16 11:50:32"
  },
  {
    "home": "Panathinaikos",
    "away": "Plzen",
    "times": {
      "Flashscore": "23:00",
      "MozzartBet": "20:00"
    },
    "league": "Europe: Europa League - Play Offs",
    "date": "19/02",
    "timestamp": "2026-02-19 11:01:11"
  },
  {
    "home": "Ludogorets",
    "away": "Ferencvaros",
    "times": {
      "Flashscore": "23:00",
      "MozzartBet": "20:00"
    },
    "league": "Europe: Europa League - Play Offs",
    "date": "19/02",
    "timestamp": "2026-02-19 11:01:11"
  },
  {
    "home": "Lille",
    "away": "Crvena zvezda",
    "times": {
      "Flashscore": "23:00",
      "MozzartBet": "20:00"
    },
    "league": "Europe: Europa League - Play Offs",
    "date": "19/02",
    "timestamp": "2026-02-19 11:01:11"
  },
  {
    "home": "Celtic",
    "away": "Stuttgart",
    "times": {
      "Flashscore": "23:00",
      "MozzartBet": "20:00"
    },
    "league": "Europe: Europa League - Play Offs",
    "date": "19/02",
    "timestamp": "2026-02-19 11:01:11"
  },
  {
    "home": "Ludogorets",
    "away": "Ferencvaros",
    "times": {
      "Flashscore": "23:00",
      "MozzartBet": "20:00"
    },
    "league": "Europe: Europa League - Play Offs",
    "date": "19/02",
    "timestamp": "2026-02-19 11:31:51"
  },
  {
    "home": "Panathinaikos",
    "away": "Plzen",
    "times": {
      "Flashscore": "23:00",
      "MozzartBet": "20:00"
    },
    "league": "Europe: Europa League - Play Offs",
    "date": "19/02",
    "timestamp": "2026-02-19 11:31:51"
  },
  {
    "home": "Celtic",
    "away": "Stuttgart",
    "times": {
      "Flashscore": "23:00",
      "MozzartBet": "20:00"
    },
    "league": "Europe: Europa League - Play Offs",
    "date": "19/02",
    "timestamp": "2026-02-19 11:31:51"
  },
  {
    "home": "Lille",
    "away": "Crvena zvezda",
    "times": {
      "Flashscore": "23:00",
      "MozzartBet": "20:00"
    },
    "league": "Europe: Europa League - Play Offs",
    "date": "19/02",
    "timestamp": "2026-02-19 11:31:51"
  },
  {
    "home": "Panathinaikos",
    "away": "Plzen",
    "times": {
      "Flashscore": "23:00",
      "MozzartBet": "20:00"
    },
    "league": "Europe: Europa League - Play Offs",
    "date": "19/02",
    "timestamp": "2026-02-19 11:36:22"
  },
  {
    "home": "Ludogorets",
    "away": "Ferencvaros",
    "times": {
      "Flashscore": "23:00",
      "MozzartBet": "20:00"
    },
    "league": "Europe: Europa League - Play Offs",
    "date": "19/02",
    "timestamp": "2026-02-19 11:36:22"
  },
  {
    "home": "Celtic",
    "away": "Stuttgart",
    "times": {
      "Flashscore": "23:00",
      "MozzartBet": "20:00"
    },
    "league": "Europe: Europa League - Play Offs",
    "date": "19/02",
    "timestamp": "2026-02-19 11:36:22"
  },
  {
    "home": "Lille",
    "away": "Crvena zvezda",
    "times": {
      "Flashscore": "23:00",
      "MozzartBet": "20:00"
    },
    "league": "Europe: Europa League - Play Offs",
    "date": "19/02",
    "timestamp": "2026-02-19 11:36:22"
  },
  {
    "home": "FC Nordsjaelland",
    "away": "Vejle BK",
    "times": {
      "Odibets": "21:00",
      "Betika": "18:00"
    },
    "league": "Football",
    "date": "20/02",
    "timestamp": "2026-02-20 11:44:51"
  },
  {
    "home": "Blackburn",
    "away": "Preston",
    "times": {
      "Flashscore": "23:00",
      "MozzartBet": "23:00",
      "Betika": "20:00"
    },
    "league": "England: Championship",
    "date": "20/02",
    "timestamp": "2026-02-20 11:44:51"
  },
  {
    "home": "Athletic Bilbao",
    "away": "Elche CF",
    "times": {
      "Odibets": "23:00",
      "Betika": "20:00"
    },
    "league": "Football",
    "date": "20/02",
    "timestamp": "2026-02-20 11:44:51"
  },
  {
    "home": "Kakamega Homeboyz",
    "away": "Sofapaka",
    "times": {
      "Flashscore": "10:00",
      "Betika": "13:00"
    },
    "league": "Football",
    "date": "20/02",
    "timestamp": "2026-02-20 12:21:22"
  },
  {
    "home": "Persija Jakarta",
    "away": "PSM Makassar",
    "times": {
      "Flashscore": "13:30",
      "Betika": "16:30"
    },
    "league": "Football",
    "date": "20/02",
    "timestamp": "2026-02-20 12:21:22"
  },
  {
    "home": "Blackburn",
    "away": "Preston",
    "times": {
      "Flashscore": "20:00",
      "MozzartBet": "23:00",
      "Betika": "23:00"
    },
    "league": "Football",
    "date": "20/02",
    "timestamp": "2026-02-20 12:21:22"
  },
  {
    "home": "Brest",
    "away": "Marseille",
    "times": {
      "Flashscore": "19:45",
      "Betika": "22:45"
    },
    "league": "Football",
    "date": "20/02",
    "timestamp": "2026-02-20 12:21:22"
  },
  {
    "home": "Oran",
    "away": "MC Alger",
    "times": {
      "Flashscore": "21:00",
      "MozzartBet": "00:00"
    },
    "league": "Football",
    "date": "20/02",
    "timestamp": "2026-02-20 12:21:22"
  },
  {
    "home": "Township Rollers",
    "away": "Extension Gunners",
    "times": {
      "Flashscore": "17:00FRO",
      "Betika": "20:00"
    },
    "league": "Football",
    "date": "20/02",
    "timestamp": "2026-02-20 12:21:22"
  },
  {
    "home": "Greuther Furth",
    "away": "Arminia Bielefeld",
    "times": {
      "Flashscore": "17:30",
      "Odibets": "20:30"
    },
    "league": "Football",
    "date": "20/02",
    "timestamp": "2026-02-20 12:21:22"
  },
  {
    "home": "Sassuolo",
    "away": "Verona",
    "times": {
      "Flashscore": "19:45",
      "MozzartBet": "22:45"
    },
    "league": "Football",
    "date": "20/02",
    "timestamp": "2026-02-20 12:21:22"
  },
  {
    "home": "Boca Juniors",
    "away": "Racing Club",
    "times": {
      "Flashscore": "23:00",
      "MozzartBet": "02:00"
    },
    "league": "Football",
    "date": "20/02",
    "timestamp": "2026-02-20 12:21:22"
  },
  {
    "home": "Rizespor",
    "away": "Kocaelispor",
    "times": {
      "Flashscore": "17:00",
      "MozzartBet": "20:00"
    },
    "league": "Football",
    "date": "20/02",
    "timestamp": "2026-02-20 12:21:22"
  }
]